{
  "_meta": {
    "schema_version": "1.0.0",
    "book_id": "marqoom76_rasail_masail_najdiyya",
    "generated_at": "2026-06-27T09:54:55.913651+00:00",
    "source": "excel",
    "excel_sha256": "081078c9aebd5735",
    "generator": "marqoom-etl/1.0"
  },
  "book": {
    "title": "كشّاف مجموعة الرسائل والمسائل النجدية",
    "author": "علماء نجد",
    "died_hijri": null,
    "category": "عقيدة",
    "book_id": "marqoom76_rasail_masail_najdiyya"
  },
  "summary": {
    "pages": null,
    "parts": null,
    "words_approx": 779803,
    "chars": 3843277,
    "surahs_detected": null
  },
  "highlights": {
    "top_purposes": {
      "_columns": [
        "category",
        "count",
        "variants_count",
        "confidence",
        "term"
      ],
      "rows": [
        [
          "الاستدلال القرآني",
          5675,
          12,
          "عالية",
          "قال الله تعالى | قال تعالى | قوله تعالى | قوله عز وجل | قوله سبحانه | في كتاب الله ..."
        ],
        [
          "الاستدلال النبوي والحديثي",
          4014,
          14,
          "عالية",
          "قال رسول الله | قال النبي | رسول الله صلى الله عليه وسلم | النبي صلى الله عليه وسلم | في الحديث | حديث ..."
        ],
        [
          "التعليل والاستنباط",
          3355,
          15,
          "متوسطة",
          "لأن | لان | فإن | فان | ولهذا | ولذلك ..."
        ],
        [
          "السؤال والفتوى والجواب",
          2078,
          13,
          "عالية",
          "سئل | سؤال | مسألة | مسائل | فأجاب | الجواب ..."
        ],
        [
          "النقل والعزو العلمي",
          1759,
          21,
          "عالية",
          "قال شيخ الإسلام | قال ابن القيم | قال الإمام أحمد | قال الشافعي | قال مالك | قال أبو حنيفة ..."
        ],
        [
          "الجدل والرد على الشبه",
          1317,
          17,
          "عالية",
          "الرد | رد على | يرد | شبهة | شبهات | زعم ..."
        ],
        [
          "النقد والإبطال والتحذير",
          1147,
          15,
          "عالية",
          "باطل | فاسد | غلط | خطأ | بدعة | ضلال ..."
        ],
        [
          "اللغة والشرح الدلالي",
          1045,
          12,
          "عالية",
          "معنى | المراد | تفسير | تأويل | لغة | العربية ..."
        ],
        [
          "الترجيح والاختيار",
          941,
          13,
          "عالية",
          "الصحيح | الصواب | الراجح | الأصح | الأظهر | الأولى ..."
        ],
        [
          "الإحالة الداخلية",
          812,
          10,
          "عالية",
          "تقدم | سبق | مر | يأتي | سيأتي | كما تقدم ..."
        ],
        [
          "الخلاف وعرض الأقوال",
          619,
          14,
          "عالية",
          "اختلف | الخلاف | فيه قولان | على قولين | قولان | قال بعضهم ..."
        ],
        [
          "الأصول والقواعد",
          575,
          13,
          "عالية",
          "الإجماع | اجماع | القياس | قاعدة | القواعد | الأصل ..."
        ]
      ]
    },
    "composite_indicators": {
      "_columns": [
        "المؤشر",
        "القيمة %",
        "أساس الحساب"
      ],
      "rows": [
        [
          "مؤشر النقل والعزو",
          7.54,
          "عدد عبارات النقل والعزو ÷ مجموع العبارات المنهجية"
        ],
        [
          "مؤشر الخلاف",
          22.87,
          "عبارات الخلاف ÷ مجموع الخلاف والترجيح والنقد"
        ],
        [
          "مؤشر الترجيح",
          60.32,
          "عبارات الترجيح ÷ مجموع الخلاف والترجيح"
        ],
        [
          "مؤشر النقد والإبطال",
          42.37,
          "عبارات النقد ÷ مجموع الخلاف والترجيح والنقد"
        ],
        [
          "مؤشر الإحالة الداخلية",
          3.48,
          "عبارات الإحالة الداخلية ÷ مجموع العبارات المنهجية"
        ],
        [
          "مؤشر اللغة والشرح",
          4.48,
          "عبارات اللغة والشرح ÷ مجموع العبارات المنهجية"
        ],
        [
          "مؤشر الجدل والرد",
          5.64,
          "عبارات الجدل والرد ÷ مجموع العبارات المنهجية"
        ],
        [
          "مؤشر الاستدلال العام",
          58.36,
          "عبارات الاستدلال القرآني والحديثي والتعليل والأصول ÷ مجموع العبارات المنهجية"
        ],
        [
          "مؤشر الطابع الفتوي",
          8.9,
          "عبارات السؤال والجواب والمسائل ÷ مجموع العبارات المنهجية"
        ],
        [
          "مؤشر تدخل المؤلفين/المجيبين",
          73.98,
          "الترجيح والنقد والجدل والتعليل ÷ النقل والعرض والترجيح والنقد والجدل والتعليل"
        ]
      ]
    },
    "top_books": {
      "_columns": [
        "book",
        "count",
        "pct_of_book_mentions",
        "domain",
        "confidence"
      ],
      "rows": [
        [
          "القرآن/كتاب الله",
          815,
          17.88,
          "قرآن",
          "عالية"
        ],
        [
          "صحيح البخاري",
          704,
          15.45,
          "حديث",
          "عالية"
        ],
        [
          "سنن أبي داود",
          567,
          12.44,
          "حديث",
          "عالية"
        ],
        [
          "صحيح مسلم",
          519,
          11.39,
          "حديث",
          "عالية"
        ],
        [
          "سنن ابن ماجه",
          479,
          10.51,
          "حديث",
          "عالية"
        ],
        [
          "جامع الترمذي/سنن الترمذي",
          299,
          6.56,
          "حديث",
          "عالية"
        ],
        [
          "الإنصاف",
          186,
          4.08,
          "فقه حنبلي",
          "عالية"
        ],
        [
          "المغني",
          129,
          2.83,
          "فقه حنبلي",
          "عالية"
        ],
        [
          "الإقناع",
          107,
          2.35,
          "فقه حنبلي",
          "عالية"
        ],
        [
          "الفروع",
          105,
          2.3,
          "فقه حنبلي",
          "عالية"
        ],
        [
          "الصحيحان",
          103,
          2.26,
          "حديث",
          "عالية"
        ],
        [
          "مجموع الفتاوى/فتاوى شيخ الإسلام",
          73,
          1.6,
          "عام",
          "عالية"
        ],
        [
          "الشرح الكبير",
          43,
          0.94,
          "فقه حنبلي",
          "عالية"
        ],
        [
          "سنن النسائي",
          40,
          0.88,
          "حديث",
          "عالية"
        ],
        [
          "المنتهى",
          37,
          0.81,
          "فقه حنبلي",
          "متوسطة"
        ],
        [
          "تفسير ابن كثير",
          36,
          0.79,
          "تفسير",
          "عالية"
        ],
        [
          "تفسير ابن جرير/جامع البيان",
          35,
          0.77,
          "تفسير",
          "عالية"
        ],
        [
          "إحياء علوم الدين",
          35,
          0.77,
          "عقيدة وردود",
          "عالية"
        ],
        [
          "مسند أحمد",
          30,
          0.66,
          "حديث",
          "عالية"
        ],
        [
          "الكافي",
          26,
          0.57,
          "فقه حنبلي",
          "متوسطة"
        ]
      ]
    },
    "top_people": {
      "_columns": [
        "person",
        "count",
        "pct_of_person_mentions",
        "category",
        "confidence"
      ],
      "rows": [
        [
          "البخاري",
          683,
          12.82,
          "محدثون",
          "عالية"
        ],
        [
          "أبو داود",
          545,
          10.23,
          "محدثون",
          "عالية"
        ],
        [
          "مسلم",
          479,
          8.99,
          "محدثون",
          "متوسطة"
        ],
        [
          "ابن ماجه",
          477,
          8.95,
          "محدثون",
          "عالية"
        ],
        [
          "الإمام أحمد",
          312,
          5.86,
          "فقهاء ومذهبيون",
          "عالية"
        ],
        [
          "الترمذي",
          298,
          5.59,
          "محدثون",
          "عالية"
        ],
        [
          "محمد بن عبد الوهاب",
          292,
          5.48,
          "أعلام نجد/مؤلفون داخل المجموعة",
          "عالية"
        ],
        [
          "ابن تيمية",
          275,
          5.16,
          "مورد سلفي حنبلي مركزي",
          "عالية"
        ],
        [
          "ابن عباس",
          273,
          5.12,
          "صحابة",
          "عالية"
        ],
        [
          "الشافعي",
          233,
          4.37,
          "فقهاء ومذهبيون",
          "عالية"
        ],
        [
          "أبو حنيفة",
          181,
          3.4,
          "فقهاء ومذهبيون",
          "عالية"
        ],
        [
          "ابن القيم",
          175,
          3.29,
          "مورد سلفي حنبلي مركزي",
          "عالية"
        ],
        [
          "عبد الله أبا بطين",
          172,
          3.23,
          "أعلام نجد/مؤلفون داخل المجموعة",
          "عالية"
        ],
        [
          "عبد اللطيف بن عبد الرحمن",
          141,
          2.65,
          "أعلام نجد/مؤلفون داخل المجموعة",
          "عالية"
        ],
        [
          "عبد الرحمن بن حسن",
          121,
          2.27,
          "أعلام نجد/مؤلفون داخل المجموعة",
          "عالية"
        ],
        [
          "ابن مسعود",
          88,
          1.65,
          "صحابة",
          "عالية"
        ],
        [
          "علي بن أبي طالب",
          62,
          1.16,
          "صحابة",
          "عالية"
        ],
        [
          "عمر بن الخطاب",
          55,
          1.03,
          "صحابة",
          "عالية"
        ],
        [
          "ابن جرير الطبري",
          47,
          0.88,
          "مفسرون",
          "عالية"
        ],
        [
          "حمد بن ناصر بن معمر",
          46,
          0.86,
          "أعلام نجد/مؤلفون داخل المجموعة",
          "عالية"
        ]
      ]
    },
    "terms": {
      "_columns": [
        "term",
        "category",
        "count",
        "pct_of_method_terms",
        "confidence"
      ],
      "rows": [
        [
          "آية",
          "الاستدلال القرآني",
          2953,
          12.65,
          "متوسطة"
        ],
        [
          "فإن",
          "التعليل والاستنباط",
          1715,
          7.35,
          "متوسطة"
        ],
        [
          "فان",
          "التعليل والاستنباط",
          1715,
          7.35,
          "متوسطة"
        ],
        [
          "الجواب",
          "السؤال والفتوى والجواب",
          839,
          3.6,
          "عالية"
        ],
        [
          "الآية",
          "الاستدلال القرآني",
          824,
          3.53,
          "عالية"
        ],
        [
          "الاية",
          "الاستدلال القرآني",
          824,
          3.53,
          "عالية"
        ],
        [
          "لأن",
          "التعليل والاستنباط",
          793,
          3.4,
          "متوسطة"
        ],
        [
          "لان",
          "التعليل والاستنباط",
          793,
          3.4,
          "متوسطة"
        ],
        [
          "النبي صلى الله عليه وسلم",
          "الاستدلال النبوي والحديثي",
          711,
          3.05,
          "عالية"
        ],
        [
          "رسول الله صلى الله عليه وسلم",
          "الاستدلال النبوي والحديثي",
          704,
          3.02,
          "عالية"
        ],
        [
          "السنة",
          "الاستدلال النبوي والحديثي",
          679,
          2.91,
          "عالية"
        ],
        [
          "القرآن",
          "الاستدلال القرآني",
          645,
          2.76,
          "عالية"
        ],
        [
          "ذكر",
          "النقل والعزو العلمي",
          597,
          2.56,
          "متوسطة"
        ],
        [
          "حديث",
          "الاستدلال النبوي والحديثي",
          586,
          2.51,
          "عالية"
        ],
        [
          "قال تعالى",
          "الاستدلال القرآني",
          551,
          2.36,
          "عالية"
        ],
        [
          "مسألة",
          "السؤال والفتوى والجواب",
          523,
          2.24,
          "عالية"
        ],
        [
          "معنى",
          "اللغة والشرح الدلالي",
          486,
          2.08,
          "عالية"
        ],
        [
          "قوله تعالى",
          "الاستدلال القرآني",
          310,
          1.33,
          "عالية"
        ],
        [
          "رواه",
          "الاستدلال النبوي والحديثي",
          305,
          1.31,
          "عالية"
        ],
        [
          "الصحيح",
          "الترجيح والاختيار",
          290,
          1.24,
          "عالية"
        ]
      ]
    },
    "schools": {
      "_columns": [
        "school",
        "count",
        "pct_of_school_mentions",
        "confidence"
      ],
      "rows": [
        [
          "أهل السنة/السلف",
          641,
          27.42,
          "عالية"
        ],
        [
          "المشركون/أهل الشرك",
          472,
          20.19,
          "عالية"
        ],
        [
          "الشافعية",
          261,
          11.16,
          "متوسطة"
        ],
        [
          "النصارى واليهود/أهل الكتاب",
          226,
          9.67,
          "عالية"
        ],
        [
          "الجهمية",
          127,
          5.43,
          "عالية"
        ],
        [
          "الحنابلة/المذهب الحنبلي",
          125,
          5.35,
          "عالية"
        ],
        [
          "الرافضة/الشيعة",
          104,
          4.45,
          "عالية"
        ],
        [
          "الخوارج",
          90,
          3.85,
          "عالية"
        ],
        [
          "الفلاسفة والمنطقيون",
          81,
          3.46,
          "عالية"
        ],
        [
          "المعتزلة",
          61,
          2.61,
          "عالية"
        ],
        [
          "الأشاعرة",
          54,
          2.31,
          "عالية"
        ],
        [
          "الحنفية",
          37,
          1.58,
          "متوسطة"
        ],
        [
          "المالكية",
          20,
          0.86,
          "متوسطة"
        ],
        [
          "الصوفية/القبورية",
          17,
          0.73,
          "عالية"
        ],
        [
          "المرجئة",
          14,
          0.6,
          "عالية"
        ],
        [
          "المتكلمون",
          8,
          0.34,
          "عالية"
        ]
      ]
    },
    "disagreement": {
      "_columns": [
        "المحور",
        "العدد",
        "النسبة من مجموع المصطلحات %",
        "درجة الثقة"
      ],
      "rows": [
        [
          "الخلاف وعرض الأقوال",
          619,
          2.65,
          "عالية"
        ],
        [
          "الترجيح والاختيار",
          941,
          4.03,
          "عالية"
        ],
        [
          "النقد والإبطال والتحذير",
          1147,
          4.91,
          "عالية"
        ],
        [
          "الجدل والرد على الشبه",
          1317,
          5.64,
          "عالية"
        ]
      ]
    },
    "executive_summary": {
      "_columns": [
        "البند",
        "النتيجة"
      ],
      "rows": [
        [
          "أبرز دلالة",
          "غلبة الاستدلال النصي والتعليل مع حضور قوي لمحاور التوحيد والردود والفتاوى العملية."
        ],
        [
          "أكثر مجال موضوعي",
          "المعاملات والأموال (3445 إشارة)"
        ],
        [
          "أكثر مورد كتابي",
          "القرآن/كتاب الله (815 إشارة)"
        ],
        [
          "أكثر علم مذكور",
          "البخاري (683 إشارة)"
        ],
        [
          "أكثر اتجاه/مدرسة",
          "أهل السنة/السلف (641 إشارة)"
        ],
        [
          "أعلى كثافة توحيد وشرك",
          "الجزء الخامس"
        ],
        [
          "أعلى كثافة معاملات",
          "الجزء الأول"
        ],
        [
          "الحد الأهم",
          "ينبغي مراجعة الألفاظ المشتركة مثل: الإمام، الشيخ، أصحابنا، شيخ الإسلام، قبل بناء أحكام تفصيلية."
        ]
      ]
    },
    "quick_reader": {
      "_columns": [
        "المحور",
        "الخلاصة"
      ],
      "rows": [
        [
          "1",
          "النص محلل كاملًا من 2581 صفحة XHTML لا من عينة."
        ],
        [
          "2",
          "أكثر الأغراض المنهجية حضورًا: الاستدلال القرآني."
        ],
        [
          "3",
          "الاستدلال العام بلغ 58.36% من مجموع العبارات المنهجية المرصودة."
        ],
        [
          "4",
          "أكثر القضايا حضورًا: المعاملات والأموال ثم التوحيد والشرك والعبادة."
        ],
        [
          "5",
          "الجزء الأول أكثر طابعًا فتويًا وفقهيًا، بينما تزداد كثافة التوحيد والردود في الأجزاء اللاحقة."
        ],
        [
          "6",
          "أكثر مورد حديثي/كتابي ظاهر: صحيح البخاري بعد القرآن/كتاب الله."
        ],
        [
          "7",
          "أكثر مدرسة/اتجاه: أهل السنة/السلف."
        ],
        [
          "8",
          "الكتاب متعدد المؤلفين؛ لذلك لا تُنسب البصمة كلها إلى عالم واحد."
        ],
        [
          "9",
          "نسب الموارد من طبقاتها: الكتب من مجموع الكتب، الأعلام من مجموع الأعلام، المدارس من مجموع المدارس."
        ],
        [
          "10",
          "الألفاظ المشتركة تحتاج مراجعة سياقية قبل الاستدلال التفصيلي."
        ]
      ]
    }
  },
  "distributions": {
    "density": {
      "_columns": [
        "part",
        "pages",
        "words",
        "فتوى/مسائل لكل 1000 كلمة",
        "استدلال قرآني لكل 1000 كلمة",
        "استدلال حديثي لكل 1000 كلمة",
        "نقد وردود لكل 1000 كلمة",
        "توحيد وشرك لكل 1000 كلمة",
        "فقه معاملات لكل 1000 كلمة"
      ],
      "rows": [
        [
          "الجزء الأول",
          763,
          217607,
          4.91,
          4.55,
          3.55,
          1.42,
          1.71,
          7.43
        ],
        [
          "الجزء الثاني",
          492,
          136128,
          3.22,
          6.46,
          5.55,
          1.25,
          4.55,
          5.65
        ],
        [
          "الجزء الثالث",
          459,
          129510,
          1.23,
          9.08,
          3.8,
          1.64,
          5.37,
          2.87
        ],
        [
          "الجزء الرابع",
          461,
          162837,
          0.91,
          12.36,
          6.25,
          1.28,
          6.84,
          1.95
        ],
        [
          "الجزء الخامس",
          406,
          133721,
          1.97,
          10.78,
          7.31,
          1.84,
          8.39,
          2.77
        ]
      ]
    }
  },
  "limits": []
}