{
  "_meta": {
    "schema_version": "1.0.0",
    "book_id": "marqoom-9",
    "generated_at": "2026-06-27T08:30:35.972926+00:00",
    "source": "excel",
    "excel_sha256": "24477a81625d0037",
    "generator": "marqoom-etl/1.0"
  },
  "book": {
    "title": "المغني شرح مختصر الخرقي",
    "author": "ابن قدامة المقدسي",
    "died_hijri": 620,
    "category": "فقه",
    "book_id": "marqoom-9"
  },
  "summary": {
    "pages": 5009,
    "parts": null,
    "words_approx": 1839773,
    "chars": 9966952,
    "surahs_detected": null
  },
  "highlights": {
    "top_purposes": {
      "_columns": [
        "الفئة",
        "العدد",
        "النسبة %",
        "أساس النسبة"
      ],
      "rows": [
        [
          "الاستدلال والتعليل",
          16123,
          42.45,
          "النسبة من مجموع عبارات القاموس المنهجي"
        ],
        [
          "النقل والعزو الحديثي",
          6620,
          17.43,
          "النسبة من مجموع عبارات القاموس المنهجي"
        ],
        [
          "الخلاف وعرض الأقوال",
          4951,
          13.03,
          "النسبة من مجموع عبارات القاموس المنهجي"
        ],
        [
          "النقد والإبطال",
          2414,
          6.36,
          "النسبة من مجموع عبارات القاموس المنهجي"
        ],
        [
          "اللغة والحدود والتعريف",
          1927,
          5.07,
          "النسبة من مجموع عبارات القاموس المنهجي"
        ],
        [
          "بنية شرح مختصر الخرقي",
          1906,
          5.02,
          "النسبة من مجموع عبارات القاموس المنهجي"
        ],
        [
          "الترجيح والاختيار",
          1761,
          4.64,
          "النسبة من مجموع عبارات القاموس المنهجي"
        ],
        [
          "الإحالة الداخلية",
          1412,
          3.72,
          "النسبة من مجموع عبارات القاموس المنهجي"
        ],
        [
          "الإجماع والاتفاق",
          871,
          2.29,
          "النسبة من مجموع عبارات القاموس المنهجي"
        ]
      ]
    },
    "top_resources": {
      "_columns": [
        "الترتيب",
        "المجال",
        "عدد موارد المجال",
        "النسبة من مجموع موارد المؤلف العامة",
        "تعليق"
      ],
      "rows": [
        [
          1,
          "فقهية ومذهبية",
          27859,
          51.01,
          "تشمل المذاهب والأئمة والكتب الفقهية واتجاهات الخلاف."
        ],
        [
          2,
          "حديثية وأثرية",
          26591,
          48.69,
          "تشمل المصادر الحديثية وأعلام الرواية وآثار الصحابة والتابعين."
        ],
        [
          3,
          "لغوية وقرآنية",
          148,
          0.27,
          "حضور محدود في العد الصريح للموارد، لا في الاستعمال اللغوي العام داخل الشرح."
        ],
        [
          4,
          "تاريخية وسيرية وتراجم",
          13,
          0.02,
          "حضور تابع، غالبًا للاستشهاد أو النقل العرضي."
        ]
      ]
    },
    "composite_indicators": {
      "_columns": [
        "المؤشر",
        "البسط",
        "المقام",
        "النسبة %",
        "أساس الحساب"
      ],
      "rows": [
        [
          "مؤشر النقل/العزو الحديثي",
          6620,
          37985,
          17.43,
          "من مجموع عبارات القاموس المنهجي المحتسبة آليًا"
        ],
        [
          "مؤشر الخلاف",
          4951,
          9126,
          54.25,
          "من مجموع عبارات الخلاف والترجيح والنقد"
        ],
        [
          "مؤشر الترجيح",
          1761,
          6712,
          26.24,
          "من مجموع عبارات الخلاف والترجيح"
        ],
        [
          "مؤشر النقد",
          2414,
          9126,
          26.45,
          "من مجموع عبارات الخلاف والترجيح والنقد"
        ],
        [
          "مؤشر الإحالة الداخلية",
          1412,
          37985,
          3.72,
          "من مجموع عبارات القاموس المنهجي المحتسبة آليًا"
        ],
        [
          "مؤشر اللغة والتعريف",
          1927,
          37985,
          5.07,
          "من مجموع عبارات القاموس المنهجي المحتسبة آليًا"
        ],
        [
          "مؤشر الاستدلال والتعليل",
          16123,
          37985,
          42.45,
          "من مجموع عبارات القاموس المنهجي المحتسبة آليًا"
        ],
        [
          "مؤشر حضور الحنابلة داخل المذاهب/الأعلام",
          8137,
          17539,
          46.39,
          "من مجموع الإشارات المصنفة آليًا للمذاهب والأعلام"
        ],
        [
          "مؤشر تركّز أعلى 10 كتب فقهية",
          2171,
          5010,
          43.33,
          "من مجموع صفحات/ملفات EPUB النصية"
        ]
      ]
    },
    "top_books": {
      "_columns": [
        "الترتيب",
        "الكتاب/المورد المصرح به",
        "المجال",
        "عدد الإحالات",
        "النسبة من إحالات الكتب المصرح بها",
        "ملاحظة منهجية"
      ],
      "rows": [
        [
          1,
          "المسند / مسند الإمام أحمد",
          "حديث",
          116,
          26.98,
          "كل ظهور صريح للعنوان العام، وغالب السياقات لمسند أحمد."
        ],
        [
          2,
          "المجرد للقاضي أبي يعلى",
          "فقه حنبلي",
          55,
          12.79,
          "عنوان فقهي حنبلي مذكور في سياقات الترجيح والروايات."
        ],
        [
          3,
          "الموطأ / موطأ مالك",
          "حديث/فقه",
          48,
          11.16,
          "أكثر السياقات مقرونة بمالك أو روايته."
        ],
        [
          4,
          "سنن أبي داود",
          "حديث",
          32,
          7.44,
          "احتسبت حين قرن أبو داود بسننه/السنن."
        ],
        [
          5,
          "الأموال لأبي عبيد",
          "فقه مال/آثار",
          20,
          4.65,
          "ميّزت عن لفظ الأموال العام."
        ],
        [
          6,
          "صحيح مسلم / صحيحه",
          "حديث",
          19,
          4.42,
          "العنوان أو نسبة الصحيح إلى مسلم."
        ],
        [
          7,
          "الجامع للقاضي أبي يعلى",
          "فقه حنبلي",
          17,
          3.95,
          "حُسب مع قرينة القاضي/أبي يعلى لتجنب عموم لفظ الجامع."
        ],
        [
          8,
          "سنن ابن ماجه",
          "حديث",
          17,
          3.95,
          "احتسبت حين قرن ابن ماجه بسننه/السنن."
        ],
        [
          9,
          "الإرشاد",
          "فقه حنبلي",
          13,
          3.02,
          null
        ],
        [
          10,
          "رؤوس المسائل",
          "فقه خلاف",
          12,
          2.79,
          null
        ],
        [
          11,
          "الشافي",
          "فقه/حديث",
          9,
          2.09,
          "العنوان صريح، لكن يحتاج تحقيقًا يدويًا لنسبة كل موضع."
        ],
        [
          12,
          "سنن الترمذي",
          "حديث",
          9,
          2.09,
          null
        ],
        [
          13,
          "الصحيحان",
          "حديث",
          8,
          1.86,
          "صيغة عنوانية/إحالية لا تفصل بين البخاري ومسلم."
        ],
        [
          14,
          "المصاحف لأبي عبيد",
          "قرآن/أثر",
          8,
          1.86,
          null
        ],
        [
          15,
          "سنن الدارقطني / كتاب العلل له",
          "حديث",
          7,
          1.63,
          null
        ],
        [
          16,
          "الهداية لأبي الخطاب",
          "فقه حنبلي",
          5,
          1.16,
          null
        ],
        [
          17,
          "المغازي",
          "سيرة/تاريخ",
          5,
          1.16,
          null
        ],
        [
          18,
          "صحيح البخاري / صحيحه",
          "حديث",
          4,
          0.93,
          null
        ],
        [
          19,
          "قضاة البصرة",
          "تاريخ/تراجم",
          4,
          0.93,
          null
        ],
        [
          20,
          "فضائل القرآن",
          "قرآن/حديث",
          3,
          0.7,
          null
        ]
      ]
    },
    "top_people": {
      "_columns": [
        "م",
        "العلم/الاسم",
        "العدد"
      ],
      "rows": [
        [
          1,
          "احمد",
          3184
        ],
        [
          2,
          "الشافعي",
          2514
        ],
        [
          3,
          "القاضي",
          1743
        ],
        [
          4,
          "مالك",
          1155
        ],
        [
          5,
          "ابو حنيفه",
          993
        ],
        [
          6,
          "داود",
          810
        ],
        [
          7,
          "الخرقي",
          594
        ],
        [
          8,
          "الحسن",
          479
        ],
        [
          9,
          "ابو الخطاب",
          477
        ],
        [
          10,
          "ابن المنذر",
          474
        ],
        [
          11,
          "اسحاق",
          242
        ],
        [
          12,
          "عطاء",
          205
        ],
        [
          13,
          "ابن عقيل",
          178
        ],
        [
          14,
          "الاوزاعي",
          144
        ],
        [
          15,
          "الثوري",
          119
        ],
        [
          16,
          "النخعي",
          101
        ],
        [
          17,
          "الزهري",
          94
        ],
        [
          18,
          "الشعبي",
          90
        ],
        [
          19,
          "ابو ثور",
          87
        ],
        [
          20,
          "ابن سيرين",
          61
        ]
      ]
    },
    "terms": {
      "_columns": [
        "م",
        "الفئة",
        "العبارة",
        "العدد"
      ],
      "rows": [
        [
          1,
          "الاستدلال والتعليل",
          "لانه",
          9912
        ],
        [
          2,
          "النقل والعزو الحديثي",
          "رواه",
          2081
        ],
        [
          3,
          "الاستدلال والتعليل",
          "لانها",
          1913
        ],
        [
          4,
          "الخلاف وعرض الأقوال",
          "احدهما",
          1677
        ],
        [
          5,
          "النقل والعزو الحديثي",
          "حديث",
          1491
        ],
        [
          6,
          "بنية شرح مختصر الخرقي",
          "قوله",
          1419
        ],
        [
          7,
          "الخلاف وعرض الأقوال",
          "روايه",
          1301
        ],
        [
          8,
          "الاستدلال والتعليل",
          "ولنا",
          1206
        ],
        [
          9,
          "النقد والإبطال",
          "لا يجوز",
          833
        ],
        [
          10,
          "الاستدلال والتعليل",
          "بدليل",
          812
        ],
        [
          11,
          "اللغة والحدود والتعريف",
          "يعني",
          747
        ],
        [
          12,
          "النقل والعزو الحديثي",
          "متفق عليه",
          711
        ],
        [
          13,
          "النقل والعزو الحديثي",
          "ابو داود",
          631
        ],
        [
          14,
          "النقل والعزو الحديثي",
          "مسلم",
          601
        ],
        [
          15,
          "الترجيح والاختيار",
          "اشبه",
          538
        ],
        [
          16,
          "اللغة والحدود والتعريف",
          "اي",
          529
        ],
        [
          17,
          "الإحالة الداخلية",
          "ذكرناه",
          472
        ],
        [
          18,
          "النقد والإبطال",
          "لا يصح",
          433
        ],
        [
          19,
          "النقد والإبطال",
          "يرد",
          385
        ],
        [
          20,
          "الاستدلال والتعليل",
          "حجه",
          370
        ]
      ]
    },
    "schools": {
      "_columns": [
        "الترتيب",
        "المدرسة/الاتجاه/المذهب",
        "عدد الورود",
        "النسبة من مجموع المدارس والاتجاهات",
        "ملاحظة منهجية"
      ],
      "rows": [
        [
          1,
          "أقوال الصحابة",
          8374,
          35.49,
          "مؤشر حضور آثار الصحابة، مع احتمال اشتراك بعض الأسماء."
        ],
        [
          2,
          "الشافعية/مذهب الشافعي",
          3726,
          15.79,
          "احتسب لفظ الشافعي بما فيه ذكر الإمام والمذهب وأصحابه."
        ],
        [
          3,
          "الحنابلة/مذهب أحمد",
          2868,
          12.16,
          "مؤشر داخلي للمذهب الحنبلي وروايات أحمد، لا يشمل كل لفظ أحمد حتى لا يطغى العد الشخصي."
        ],
        [
          4,
          "أقوال التابعين",
          2794,
          11.84,
          "مؤشر حضور طبقة التابعين وفق الأعلام المختارة والعبارات العامة."
        ],
        [
          5,
          "المالكية/مذهب مالك",
          2181,
          9.24,
          "احتسب لفظ مالك بوصفه علمًا ومدخلًا مذهبيًا في المقارنة."
        ],
        [
          6,
          "الحنفية/أصحاب الرأي",
          1865,
          7.9,
          "جمعت رموز الاتجاه الحنفي وعبارة أصحاب الرأي."
        ],
        [
          7,
          "أهل العلم/الجمهور",
          1486,
          6.3,
          "عبارات جامعة عابرة للمذاهب."
        ],
        [
          8,
          "الظاهرية/داود",
          160,
          0.68,
          "فُصل داود الظاهري عن أبي داود قدر الإمكان."
        ],
        [
          9,
          "الأمصار والمدارس الإقليمية",
          121,
          0.51,
          "مؤشرات مدرسية مكانية."
        ],
        [
          10,
          "أهل الحديث/المحدثون",
          20,
          0.08,
          "حضور محدود بوصفه اتجاهًا صريحًا."
        ]
      ]
    },
    "disagreement": {
      "_columns": [
        "المستند",
        "العدد",
        "تفصيل العبارات"
      ],
      "rows": [
        [
          "السنة/الحديث",
          5167,
          "قال رسول الله: 347؛ قول النبي: 393؛ عن النبي: 777؛ عن رسول الله: 78؛ حديث: 1491؛ رواه: 2081"
        ],
        [
          "اللغة والتعريف",
          1146,
          "في اللغه: 20؛ وفي الشرع: 1؛ معناه: 162؛ يعني: 747؛ يقال: 216"
        ],
        [
          "القياس",
          976,
          "قياس: 293؛ قياسا: 97؛ والقياس: 48؛ اشبه: 538"
        ],
        [
          "الأصل/الاستصحاب",
          812,
          "والاصل: 219؛ اصل: 251؛ الاصل بقاء: 47؛ لان الاصل: 295"
        ],
        [
          "قول الصحابي/الأثر",
          765,
          "عن عمر: 240؛ عن علي: 230؛ عن ابن عمر: 108؛ عن ابن عباس: 115؛ عن ابن مسعود: 35؛ عن ابي هريره: 37"
        ],
        [
          "القرآن",
          685,
          "قال الله: 269؛ لقول الله: 301؛ كتاب الله: 74؛ في كتاب الله: 41"
        ],
        [
          "الإجماع/عدم الخلاف",
          548,
          "اجماع: 92؛ اجمع: 302؛ لا خلاف: 115؛ لا نعلم فيه خلافا: 39"
        ]
      ]
    },
    "executive_summary": {
      "_columns": [
        "م",
        "النتيجة"
      ],
      "rows": [
        [
          "1",
          "المغني في هذا الفحص نص ضخم يقارب 1.84 مليون كلمة، مما يجعله مناسبًا جدًا للتحليل المصطلحي واسع النطاق."
        ],
        [
          "2",
          "بنية الفهرس تكشف طبيعة الكتاب العملية: أكثر من خمسة آلاف فصل ونحو ألفي مسألة."
        ],
        [
          "3",
          "الاستدلال والتعليل هو أعلى غرض منهجي في القاموس الآلي، لا مجرد نقل للأقوال."
        ],
        [
          "4",
          "عبارة “لأنه” وحدها من أكثر مفاتيح التعليل حضورًا، بما يعكس تفسير الحكم وعلله لا الاكتفاء بعرضه."
        ],
        [
          "5",
          "حضور “ولنا” بارز، وهو مؤشر على بناء الجواب الحنبلي في مقابلة الأقوال المخالفة."
        ],
        [
          "6",
          "النقل الحديثي حاضر بوضوح داخل الكتاب، لكنه ليس هو المحور الوحيد؛ بل يخدم البناء الفقهي المقارن."
        ],
        [
          "7",
          "أكثر الكتب امتدادًا: الصلاة، البيوع، الحج، الطهارة، النكاح، وهذا يوضح مراكز الكثافة العلمية."
        ],
        [
          "8",
          "حضور الشافعي وأبي حنيفة ومالك وداود وابن المنذر وأصحاب الرأي يجعل الكتاب مادة خصبة لرسم خريطة الخلاف الفقهي."
        ],
        [
          "9",
          "الإحالات الداخلية أقل من التعليل والنقل، لكنها تكشف ترابطًا بنائيًا بين المواضع."
        ],
        [
          "10",
          "النتائج لا تُقرأ بوصفها أحكامًا نهائية على مذهب ابن قدامة، بل بوصفها خريطة رقمية أولى قابلة للتحقق والمراجعة."
        ]
      ]
    },
    "quick_reader": {
      "_columns": [
        "م",
        "العنوان",
        "الخلاصة"
      ],
      "rows": [
        [
          "1",
          "حجم النص",
          "1,839,773 كلمة تقريبًا، في 5,010 ملف XHTML داخل EPUB"
        ],
        [
          "2",
          "نوع الكتاب",
          "فقه مقارن مع بنية شرح لمختصر الخرقي؛ وليس تفسيرًا مسندًا ولا شرح حديث مستقلًا"
        ],
        [
          "3",
          "الفهرس",
          "7,668 مدخلًا: 5,353 فصلًا، 1,956 مسألة، 69 كتابًا"
        ],
        [
          "4",
          "الغرض الأعلى",
          "الاستدلال والتعليل: 16,123 = 42.45% من عبارات القاموس"
        ],
        [
          "5",
          "أبرز بنية مذهبية",
          "الحضور الحنبلي/أصحابنا: 8,137 إشارة ضمن قاموس المذاهب والأعلام المصنف آليًا"
        ],
        [
          "6",
          "أكثر الكتب كثافة",
          "كتاب الصلاه ثم كتاب البيوع ثم كتاب الحج بحسب عدد الكلمات"
        ],
        [
          "7",
          "النقل الحديثي",
          "17.43% من مجموع عبارات القاموس المنهجي"
        ],
        [
          "8",
          "الخلاف والترجيح والنقد",
          "مؤشر الخلاف 54.25%، والترجيح 26.24%، والنقد 26.45% حسب أساس كل مؤشر"
        ],
        [
          "9",
          "حدود الثقة",
          "العدّ آلي لعبارات ظاهرة بعد التطبيع؛ يحتاج أعلى المداخل ومواطن الأعلام المشتركة إلى مراجعة يدوية"
        ],
        [
          "10",
          "العنوان المقترح",
          "الكشّاف المنهجي الرقمي: المغني لابن قدامة بالأرقام"
        ]
      ]
    }
  },
  "distributions": {},
  "limits": []
}