{
  "_meta": {
    "schema_version": "1.0.0",
    "book_id": "marqoom-6",
    "generated_at": "2026-06-27T08:30:34.038177+00:00",
    "source": "excel",
    "excel_sha256": "2ed8e65a6e2fcfd7",
    "generator": "marqoom-etl/1.0"
  },
  "book": {
    "title": "جامع البيان في تأويل القرآن",
    "author": "ابن جرير الطبري",
    "died_hijri": 310,
    "category": "تفسير",
    "book_id": "marqoom-6"
  },
  "summary": {
    "pages": null,
    "parts": null,
    "words_approx": null,
    "chars": null,
    "surahs_detected": null
  },
  "highlights": {
    "top_resources": {
      "_columns": [
        "المجال",
        "العدد",
        "نسبة الحضور من مجموع موارد المجال",
        "أمثلة ممثلة"
      ],
      "rows": [
        [
          "تفسير وأثر",
          43314,
          0.4498800361449538,
          "ابن عباس, مجاهد, قتادة, الحسن, ابن جريج, ابن زيد, السدي, الضحاك, عكرمة, سعيد بن جبير, ابن مسعود, الربيع بن أنس, أبي بن كعب, الكلبي, أبو العالية"
        ],
        [
          "رواية وطرق إسناد",
          27538,
          0.2860229125769898,
          "المثنى, ابن أبي نجيح, أسباط, ابن حميد, ابن وهب, بشر بن معاذ, يونس بن عبد الأعلى, سعيد بن أبي عروبة, القاسم, حجاج بن محمد"
        ],
        [
          "مصادر كتابية/استدلالية",
          10501,
          0.1090684365230216,
          "القرآن/كتاب الله, التوراة, الإنجيل, أم الكتاب, صحف إبراهيم وموسى, الزبور, اللوح المحفوظ"
        ],
        [
          "لغة ونحو",
          7808,
          0.08109764330747099,
          "قتادة, الفراء, سيبويه, الكسائي, الأخفش, أبو عمرو بن العلاء"
        ],
        [
          "تاريخ وسيرة",
          2872,
          0.02982997330674394,
          "ابن إسحاق"
        ],
        [
          "فقه وحديث وأثر عام",
          2201,
          0.02286064458500815,
          "عبد الله بن عمر, عائشة, عمر بن الخطاب"
        ],
        [
          "قراءات ومصاحف",
          2045,
          0.02124035355581175,
          "مصحف عبد الله بن مسعود, مصحف أبي بن كعب, مصاحف المسلمين/الأمصار, ابن مسعود, أبي بن كعب, الكسائي, عاصم القارئ, أبو عمرو بن العلاء, ابن عامر, حمزة القارئ, نافع القارئ"
        ]
      ]
    },
    "top_books": {
      "_columns": [
        "المورد/الكتاب",
        "المجال",
        "المجموعة",
        "العدد",
        "نسبة الحضور من إحالات الكتب/المصادر",
        "نسبة الحضور من الموارد العامة",
        "تنبيه التصنيف",
        "النمط المستخدم"
      ],
      "rows": [
        [
          "القرآن/كتاب الله",
          "مصدر تفسيري/استدلالي",
          "المصادر القرآنية",
          8579,
          0.7882212421903712,
          0.05453424361468147,
          "الذكر القرآني الصريح أو الوصفي",
          "القرآن=3888؛ القران=3888؛ كتاب الله=584؛ كتاب ربنا=2؛ كتاب ربه=11؛ الفرقان=206"
        ],
        [
          "التوراة",
          "مصدر كتابي سابق",
          "الكتب السماوية السابقة",
          809,
          0.07432929070194781,
          0.00514258107987846,
          "مذكور في سياقات أهل الكتاب وبني إسرائيل",
          "التوراة=809"
        ],
        [
          "الإنجيل",
          "مصدر كتابي سابق",
          "الكتب السماوية السابقة",
          666,
          0.06119073869900771,
          0.004233571074411686,
          "ذكر نصي/كتابي داخل سياقات أهل الكتاب والقصص.",
          "الإنجيل=333؛ الانجيل=333"
        ],
        [
          "أم الكتاب",
          "مصدر كتابي/مصطلح قرآني",
          "المصادر القرآنية",
          286,
          0.02627710400588019,
          0.001818020010933547,
          "مورد قرآني/مصطلح قرآني؛ لا يعني كتابًا مؤلفًا مستقلًا.",
          "أم الكتاب=143؛ ام الكتاب=143"
        ],
        [
          "مصحف عبد الله بن مسعود",
          "مصدر قرائي/مصحفي",
          "المصادر القرائية/المصحفية",
          205,
          0.01883498713708195,
          0.001303126231613207,
          "مورد قرائي/مصحفي؛ قد يدل على قراءة أو مصحف منسوب.",
          "مصحف عبد الله=20؛ مصحف ابن مسعود=2؛ في مصحف عبد الله=20؛ قراءة عبد الله=163"
        ],
        [
          "مصحف أبي بن كعب",
          "مصدر قرائي/مصحفي",
          "المصادر القرائية/المصحفية",
          138,
          0.01267916207276736,
          0.0008772264388420612,
          "مورد قرائي/مصحفي؛ قد يدل على قراءة أو مصحف منسوب.",
          "مصحف أبي=2؛ مصحف ابي=2؛ قراءة أبي=67؛ قراءة ابي=67"
        ],
        [
          "صحف إبراهيم وموسى",
          "مصدر كتابي سابق",
          "الكتب السماوية السابقة",
          64,
          0.005880191106210952,
          0.0004068296527963182,
          "ذكر نصي/كتابي داخل سياقات أهل الكتاب والقصص.",
          "صحف إبراهيم=20؛ صحف ابراهيم=20؛ صحف موسى=11؛ صحف ابراهيم وموسى=13"
        ],
        [
          "الزبور",
          "مصدر كتابي سابق",
          "الكتب السماوية السابقة",
          61,
          0.005604557148107313,
          0.0003877595128214908,
          "ذكر نصي/كتابي داخل سياقات أهل الكتاب والقصص.",
          "الزبور=61"
        ],
        [
          "مصاحف المسلمين/الأمصار",
          "مصدر قرائي/مصحفي",
          "موارد كتابية/تفسيرية",
          40,
          0.003675119441381845,
          0.0002542685329976989,
          "مورد مصرح يحتاج فحص سياق عند التفصيل.",
          "مصاحف المسلمين=32؛ مصاحف أهل الأمصار=2؛ مصاحف اهل الامصار=2؛ مصحف الإمام=2؛ مصحف الامام=2"
        ],
        [
          "اللوح المحفوظ",
          "مصدر غيبي/كتابي",
          "موارد كتابية/غيبية",
          36,
          0.00330760749724366,
          0.000228841679697929,
          "مصطلح كتابي/غيبـي مذكور في النص.",
          "اللوح المحفوظ=27؛ لوح محفوظ=9"
        ]
      ]
    },
    "top_people": {
      "_columns": [
        "العلم",
        "المدرسة/الانتماء",
        "الدور في النص",
        "العدد",
        "نسبة الحضور من الأعلام",
        "نسبة الحضور من الموارد العامة",
        "النمط المستخدم"
      ],
      "rows": [
        [
          "المثنى",
          "شيخ الطبري/طريق",
          "رواية",
          9390,
          0.1210613171058739,
          0.05968953812120981,
          "المثنى=4695؛ المثني=4695"
        ],
        [
          "ابن عباس",
          "صحابي/مدرسة مكة",
          "تفسير/أثر",
          7405,
          0.09546954772832758,
          0.047071462171199,
          "ابن عباس=7323؛ عبد الله بن عباس=82"
        ],
        [
          "ابن أبي نجيح",
          "راوٍ/مكة",
          "طريق مجاهد",
          7272,
          0.09375483471713682,
          0.04622601929898165,
          "ابن أبي نجيح=3636؛ ابن ابي نجيح=3636"
        ],
        [
          "مجاهد",
          "تابعي/مدرسة مكة",
          "تفسير",
          7219,
          0.09307152802846681,
          0.0458891134927597,
          "مجاهد=7213؛ مجاهد بن جبر=6"
        ],
        [
          "قتادة",
          "تابعي/مدرسة البصرة",
          "تفسير/لغة",
          6814,
          0.08785003352070549,
          0.043314644596158,
          "قتادة=6763؛ قتاده=49؛ قتادة بن دعامة=2"
        ],
        [
          "الحسن",
          "اسم مشترك/يحتاج مراجعة",
          "تفسير",
          6530,
          0.0841885410757568,
          0.04150933801187434,
          "الحسن=6530"
        ],
        [
          "أسباط",
          "راوٍ/كوفة",
          "طريق السدي",
          3940,
          0.05079676138414729,
          0.02504545050027334,
          "أسباط بن نصر=38؛ اسباط بن نصر=38؛ أسباط=1932؛ اسباط=1932"
        ],
        [
          "ابن حميد",
          "شيخ الطبري/طريق",
          "رواية",
          3116,
          0.04017327626218348,
          0.01980751872052074,
          "ابن حميد=3018؛ محمد بن حميد=98"
        ],
        [
          "ابن جريج",
          "تابع تابعي/مكة",
          "تفسير",
          2895,
          0.0373240162962199,
          0.01840268507570846,
          "ابن جريج=2892؛ عبد الملك بن جريج=3"
        ],
        [
          "ابن إسحاق",
          "مؤرخ/سيرة",
          "تاريخ/سيرة",
          2872,
          0.03702748697849518,
          0.01825648066923478,
          "ابن إسحاق=1070؛ ابن اسحاق=1070؛ محمد بن إسحاق=366؛ محمد بن اسحاق=366"
        ],
        [
          "ابن وهب",
          "راوٍ/مصر",
          "طريق رواية",
          2651,
          0.03417822701253159,
          0.01685164702442249,
          "ابن وهب=2606؛ عبد الله بن وهب=45"
        ],
        [
          "ابن زيد",
          "تابعي/مدرسة المدينة",
          "تفسير",
          2371,
          0.03056830488370894,
          0.0150717672934386,
          "ابن زيد=2323؛ عبد الرحمن بن زيد=48"
        ],
        [
          "السدي",
          "تابعي/مدرسة الكوفة",
          "تفسير",
          2326,
          0.02998813882729101,
          0.01478571519381619,
          "السدي=2282؛ إسماعيل السدي=22؛ اسماعيل السدي=22"
        ],
        [
          "الضحاك",
          "تابعي/تفسير",
          "تفسير",
          1915,
          0.02468928884534062,
          0.01217310601726483,
          "الضحاك=1806؛ الضحاك بن مزاحم=109"
        ],
        [
          "عكرمة",
          "تابعي/مدرسة مكة",
          "تفسير",
          1896,
          0.02444432984374194,
          0.01205232846409093,
          "عكرمة=1868؛ عكرمة مولى ابن عباس=28"
        ],
        [
          "سعيد بن جبير",
          "تابعي/مدرسة مكة",
          "تفسير",
          1763,
          0.02272961683255118,
          0.01120688559187358,
          "سعيد بن جبير=1763"
        ],
        [
          "عبد الله بن عمر",
          "صحابي",
          "أثر/فقه",
          1042,
          0.01343406735083286,
          0.006623695284590055,
          "ابن عمر=654؛ عبد الله بن عمر=383؛ عبدالله بن عمر=5"
        ],
        [
          "ابن مسعود",
          "صحابي/مدرسة الكوفة",
          "تفسير/قراءات",
          1030,
          0.01327935640245475,
          0.006547414724690746,
          "ابن مسعود=729؛ عبد الله بن مسعود=297؛ عبدالله بن مسعود=4"
        ],
        [
          "عائشة",
          "صحابية",
          "حديث/فقه",
          845,
          0.0108942292816255,
          0.005371422759576389,
          "عائشة=844؛ عائشه=1"
        ],
        [
          "الفراء",
          "لغوي/كوفي",
          "لغة/نحو",
          634,
          0.008173895105977,
          0.004030156248013527,
          "الفراء=627؛ يحيى بن زياد=7"
        ]
      ]
    },
    "schools": {
      "_columns": [
        "المدرسة/الاتجاه",
        "النوع",
        "العدد",
        "نسبة الحضور من المدارس",
        "نسبة الحضور من الموارد العامة",
        "أبرز الممثلين/النمط",
        "درجة الثقة"
      ],
      "rows": [
        [
          "مدرسة مكة / تفسير ابن عباس",
          "مدرسة/اتجاه تفسيري أو طبقة نقل",
          28450,
          0.4131211337960677,
          0.1808484940946133,
          "ابن عباس, مجاهد, عكرمة, سعيد بن جبير, ابن جريج, ابن أبي نجيح",
          "عالية"
        ],
        [
          "شيوخ وطرق الطبري المباشرة",
          "مدرسة/اتجاه تفسيري أو طبقة نقل",
          16140,
          0.2343681933029361,
          0.1025973530645715,
          "المثنى, بشر بن معاذ, يونس بن عبد الأعلى, ابن حميد, القاسم, ابن وهب, حجاج بن محمد",
          "متوسطة"
        ],
        [
          "مدرسة الكوفة",
          "مدرسة/اتجاه تفسيري أو طبقة نقل",
          8258,
          0.1199140359538814,
          0.05249373863737493,
          "السدي, ابن مسعود, الكلبي, أسباط, الفراء, الكسائي, حمزة القارئ, عاصم القارئ",
          "عالية"
        ],
        [
          "مدرسة البصرة",
          "مدرسة/اتجاه تفسيري أو طبقة نقل",
          7762,
          0.1127116429007057,
          0.04934080882820346,
          "قتادة, الحسن البصري, أبو العالية, الربيع بن أنس, سعيد بن أبي عروبة",
          "عالية"
        ],
        [
          "صحابة عامة",
          "مدرسة/اتجاه تفسيري أو طبقة نقل",
          2999,
          0.04354834025498795,
          0.01906378326150247,
          "علي بن أبي طالب, عمر بن الخطاب, عبد الله بن عمر, عائشة, أبي بن كعب",
          "متوسطة"
        ],
        [
          "موارد السيرة والتاريخ",
          "مدرسة/اتجاه تفسيري أو طبقة نقل",
          2872,
          0.04170417913048529,
          0.01825648066923478,
          "ابن إسحاق",
          "عالية"
        ],
        [
          "مدرسة المدينة",
          "مدرسة/اتجاه تفسيري أو طبقة نقل",
          2374,
          0.03447274416983707,
          0.01509083743341343,
          "ابن زيد, نافع القارئ",
          "عالية"
        ],
        [
          "مدرسة الشام",
          "مدرسة/اتجاه تفسيري أو طبقة نقل",
          11,
          0.0001597304910986554,
          6.99238465743672e-05,
          "ابن عامر",
          "عالية"
        ]
      ]
    }
  },
  "distributions": {},
  "limits": []
}