{
  "_meta": {
    "schema_version": "1.0.0",
    "book_id": "marqoom-37",
    "generated_at": "2026-06-27T08:30:54.455858+00:00",
    "source": "excel",
    "excel_sha256": "d421147535d85455",
    "generator": "marqoom-etl/1.0"
  },
  "book": {
    "title": "شرح معاني الآثار",
    "author": "الطحاوي",
    "died_hijri": 321,
    "category": "حديث",
    "book_id": "marqoom-37"
  },
  "summary": {
    "pages": null,
    "parts": null,
    "words_approx": null,
    "chars": null,
    "surahs_detected": null
  },
  "highlights": {
    "top_resources": {
      "_columns": [
        "الفئة",
        "المورد/المصدر",
        "عدد الإشارات اللفظية",
        "أساس النسبة",
        "النسبة %",
        "تنبيه منهجي"
      ],
      "rows": [
        [
          "خريطة الموارد العامة",
          "السنة/حديث النبي",
          10629,
          "من مجموع إشارات الموارد العامة",
          57.62,
          "حساب لفظي آلي لا يعني مقدار الاعتماد النهائي"
        ],
        [
          "المدارس والاتجاهات",
          "الصحابة",
          4596,
          "من مجموع إشارات المدارس والاتجاهات",
          65.3,
          "نسبة حضور لا نسبة استفادة مطلقة"
        ],
        [
          "خريطة الموارد العامة",
          "آثار الصحابة",
          4090,
          "من مجموع إشارات الموارد العامة",
          22.17,
          "حساب لفظي آلي لا يعني مقدار الاعتماد النهائي"
        ],
        [
          "خريطة الموارد العامة",
          "آثار التابعين",
          1772,
          "من مجموع إشارات الموارد العامة",
          9.61,
          "حساب لفظي آلي لا يعني مقدار الاعتماد النهائي"
        ],
        [
          "خريطة الموارد العامة",
          "أقوال الفقهاء الآخرين",
          1180,
          "من مجموع إشارات الموارد العامة",
          6.4,
          "حساب لفظي آلي لا يعني مقدار الاعتماد النهائي"
        ],
        [
          "المدارس والاتجاهات",
          "التابعون",
          1071,
          "من مجموع إشارات المدارس والاتجاهات",
          15.22,
          "نسبة حضور لا نسبة استفادة مطلقة"
        ],
        [
          "المدارس والاتجاهات",
          "المالكية/أهل المدينة",
          948,
          "من مجموع إشارات المدارس والاتجاهات",
          13.47,
          "نسبة حضور لا نسبة استفادة مطلقة"
        ],
        [
          "المدارس والاتجاهات",
          "الحنفية/أهل الكوفة",
          405,
          "من مجموع إشارات المدارس والاتجاهات",
          5.75,
          "نسبة حضور لا نسبة استفادة مطلقة"
        ],
        [
          "خريطة الموارد العامة",
          "أقوال فقهاء الكوفة",
          394,
          "من مجموع إشارات الموارد العامة",
          2.14,
          "حساب لفظي آلي لا يعني مقدار الاعتماد النهائي"
        ],
        [
          "خريطة الموارد العامة",
          "كتاب الله",
          383,
          "من مجموع إشارات الموارد العامة",
          2.08,
          "حساب لفظي آلي لا يعني مقدار الاعتماد النهائي"
        ],
        [
          "الكتب المصرح بها/الألفاظ الكتابية",
          "كتاب الله",
          66,
          "من مجموع إحالات الكتب المصرح بها المرصودة",
          100,
          "ألفاظ عامة أو عناوين؛ تحتاج تحريراً عند النشر"
        ],
        [
          "المدارس والاتجاهات",
          "الشافعية",
          18,
          "من مجموع إشارات المدارس والاتجاهات",
          0.26,
          "نسبة حضور لا نسبة استفادة مطلقة"
        ]
      ]
    },
    "top_books": {
      "_columns": [
        "الفئة",
        "المورد/المصدر",
        "عدد الإشارات اللفظية",
        "أساس النسبة",
        "النسبة %",
        "تنبيه منهجي"
      ],
      "rows": [
        [
          "خريطة الموارد العامة",
          "السنة/حديث النبي",
          10629,
          "من مجموع إشارات الموارد العامة",
          57.62,
          "حساب لفظي آلي لا يعني مقدار الاعتماد النهائي"
        ],
        [
          "المدارس والاتجاهات",
          "الصحابة",
          4596,
          "من مجموع إشارات المدارس والاتجاهات",
          65.3,
          "نسبة حضور لا نسبة استفادة مطلقة"
        ],
        [
          "خريطة الموارد العامة",
          "آثار الصحابة",
          4090,
          "من مجموع إشارات الموارد العامة",
          22.17,
          "حساب لفظي آلي لا يعني مقدار الاعتماد النهائي"
        ],
        [
          "خريطة الموارد العامة",
          "آثار التابعين",
          1772,
          "من مجموع إشارات الموارد العامة",
          9.61,
          "حساب لفظي آلي لا يعني مقدار الاعتماد النهائي"
        ],
        [
          "خريطة الموارد العامة",
          "أقوال الفقهاء الآخرين",
          1180,
          "من مجموع إشارات الموارد العامة",
          6.4,
          "حساب لفظي آلي لا يعني مقدار الاعتماد النهائي"
        ],
        [
          "المدارس والاتجاهات",
          "التابعون",
          1071,
          "من مجموع إشارات المدارس والاتجاهات",
          15.22,
          "نسبة حضور لا نسبة استفادة مطلقة"
        ],
        [
          "المدارس والاتجاهات",
          "المالكية/أهل المدينة",
          948,
          "من مجموع إشارات المدارس والاتجاهات",
          13.47,
          "نسبة حضور لا نسبة استفادة مطلقة"
        ],
        [
          "المدارس والاتجاهات",
          "الحنفية/أهل الكوفة",
          405,
          "من مجموع إشارات المدارس والاتجاهات",
          5.75,
          "نسبة حضور لا نسبة استفادة مطلقة"
        ],
        [
          "خريطة الموارد العامة",
          "أقوال فقهاء الكوفة",
          394,
          "من مجموع إشارات الموارد العامة",
          2.14,
          "حساب لفظي آلي لا يعني مقدار الاعتماد النهائي"
        ],
        [
          "خريطة الموارد العامة",
          "كتاب الله",
          383,
          "من مجموع إشارات الموارد العامة",
          2.08,
          "حساب لفظي آلي لا يعني مقدار الاعتماد النهائي"
        ],
        [
          "الكتب المصرح بها/الألفاظ الكتابية",
          "كتاب الله",
          66,
          "من مجموع إحالات الكتب المصرح بها المرصودة",
          100,
          "ألفاظ عامة أو عناوين؛ تحتاج تحريراً عند النشر"
        ],
        [
          "المدارس والاتجاهات",
          "الشافعية",
          18,
          "من مجموع إشارات المدارس والاتجاهات",
          0.26,
          "نسبة حضور لا نسبة استفادة مطلقة"
        ]
      ]
    },
    "top_people": {
      "_columns": [
        "التصنيف",
        "العلم",
        "عدد الإشارات",
        "أساس النسبة",
        "النسبة %",
        "ملاحظة"
      ],
      "rows": [
        [
          "فقيه/تابعي/مورد فقهي",
          "مالك",
          922,
          "من مجموع الأعلام المرصودة",
          11.85,
          "رصد لفظي آلي"
        ],
        [
          "صحابي/راوٍ أعلى",
          "عائشة",
          917,
          "من مجموع الأعلام المرصودة",
          11.78,
          "رصد لفظي آلي"
        ],
        [
          "صحابي/راوٍ أعلى",
          "ابن عمر",
          906,
          "من مجموع الأعلام المرصودة",
          11.64,
          "رصد لفظي آلي"
        ],
        [
          "صحابي/راوٍ أعلى",
          "ابن عباس",
          875,
          "من مجموع الأعلام المرصودة",
          11.24,
          "رصد لفظي آلي"
        ],
        [
          "صحابي/راوٍ أعلى",
          "جابر",
          625,
          "من مجموع الأعلام المرصودة",
          8.03,
          "رصد لفظي آلي"
        ],
        [
          "فقيه/تابعي/مورد فقهي",
          "عطاء",
          435,
          "من مجموع الأعلام المرصودة",
          5.59,
          "رصد لفظي آلي"
        ],
        [
          "فقيه/تابعي/مورد فقهي",
          "الزهري",
          425,
          "من مجموع الأعلام المرصودة",
          5.46,
          "رصد لفظي آلي"
        ],
        [
          "فقيه/تابعي/مورد فقهي",
          "الحسن",
          424,
          "من مجموع الأعلام المرصودة",
          5.45,
          "رصد لفظي آلي"
        ],
        [
          "صحابي/راوٍ أعلى",
          "عبد الله بن عمر",
          317,
          "من مجموع الأعلام المرصودة",
          4.07,
          "رصد لفظي آلي"
        ],
        [
          "صحابي/راوٍ أعلى",
          "عمر بن الخطاب",
          247,
          "من مجموع الأعلام المرصودة",
          3.17,
          "رصد لفظي آلي"
        ],
        [
          "صحابي/راوٍ أعلى",
          "أنس بن مالك",
          185,
          "من مجموع الأعلام المرصودة",
          2.38,
          "رصد لفظي آلي"
        ],
        [
          "فقيه/تابعي/مورد فقهي",
          "مجاهد",
          156,
          "من مجموع الأعلام المرصودة",
          2,
          "رصد لفظي آلي"
        ],
        [
          "فقيه/تابعي/مورد فقهي",
          "الشعبي",
          140,
          "من مجموع الأعلام المرصودة",
          1.8,
          "رصد لفظي آلي"
        ],
        [
          "فقيه/تابعي/مورد فقهي",
          "سعيد بن المسيب",
          136,
          "من مجموع الأعلام المرصودة",
          1.75,
          "رصد لفظي آلي"
        ],
        [
          "فقيه/تابعي/مورد فقهي",
          "أبو يوسف",
          133,
          "من مجموع الأعلام المرصودة",
          1.71,
          "رصد لفظي آلي"
        ],
        [
          "فقيه/تابعي/مورد فقهي",
          "أبو حنيفة",
          124,
          "من مجموع الأعلام المرصودة",
          1.59,
          "رصد لفظي آلي"
        ],
        [
          "صحابي/راوٍ أعلى",
          "علي بن أبي طالب",
          116,
          "من مجموع الأعلام المرصودة",
          1.49,
          "رصد لفظي آلي"
        ],
        [
          "فقيه/تابعي/مورد فقهي",
          "الأوزاعي",
          111,
          "من مجموع الأعلام المرصودة",
          1.43,
          "رصد لفظي آلي"
        ],
        [
          "صحابي/راوٍ أعلى",
          "عبد الله بن مسعود",
          99,
          "من مجموع الأعلام المرصودة",
          1.27,
          "رصد لفظي آلي"
        ],
        [
          "فقيه/تابعي/مورد فقهي",
          "محمد بن الحسن",
          94,
          "من مجموع الأعلام المرصودة",
          1.21,
          "رصد لفظي آلي"
        ]
      ]
    },
    "terms": {
      "_columns": [
        "المؤشر المنهجي",
        "عدد الوحدات",
        "النسبة من الوحدات النصية %",
        "وصف الاستخدام"
      ],
      "rows": [
        [
          "علل وإسناد",
          4938,
          99.26,
          "حضور صيغ الأداء والرواية والنقد الإسنادي والاتصال والانقطاع."
        ],
        [
          "ترجيح طحاوي",
          1300,
          26.13,
          "مواضع قال أبو جعفر وما اتصل بها من تقرير أو دفع أو تصحيح."
        ],
        [
          "كِتَابُ الصَّلَاةِ",
          1275,
          25.63,
          "عدد الوحدات النصية تحت هذا الكتاب"
        ],
        [
          "قياس ونظر",
          694,
          13.95,
          "مواضع النظر والقياس والتعليل والمعنى."
        ],
        [
          "جمع بين الآثار",
          494,
          9.93,
          "مواضع الاحتمال والتأويل والجمع بين الروايات."
        ],
        [
          "كِتَابُ الْكَرَاهَةِ",
          485,
          9.75,
          "عدد الوحدات النصية تحت هذا الكتاب"
        ],
        [
          "كِتَابُ مَنَاسِكِ الْحَجِّ",
          478,
          9.61,
          "عدد الوحدات النصية تحت هذا الكتاب"
        ],
        [
          "كتاب الطهارة",
          471,
          9.47,
          "عدد الوحدات النصية تحت هذا الكتاب"
        ],
        [
          "اختلاف فقهي",
          311,
          6.25,
          "مواضع ذكر أقوال الفقهاء والمدارس."
        ],
        [
          "كِتَابُ السِّيَرِ",
          271,
          5.45,
          "عدد الوحدات النصية تحت هذا الكتاب"
        ],
        [
          "كِتَابُ الصِّيَامِ",
          205,
          4.12,
          "عدد الوحدات النصية تحت هذا الكتاب"
        ],
        [
          "كِتَابُ الْبُيُوعِ",
          197,
          3.96,
          "عدد الوحدات النصية تحت هذا الكتاب"
        ],
        [
          "نسخ/تاريخ الحكم",
          189,
          3.8,
          "مواضع النسخ أو دعوى تقدم الحكم وتأخره."
        ],
        [
          "كِتَابُ الصَّيْدِ وَالذَّبَائِحِ وَالْأَضَاحِيِّ",
          159,
          3.2,
          "عدد الوحدات النصية تحت هذا الكتاب"
        ],
        [
          "كِتَابُ الْجَنَائِزِ",
          158,
          3.18,
          "عدد الوحدات النصية تحت هذا الكتاب"
        ],
        [
          "كِتَابُ النِّكَاحِ",
          152,
          3.06,
          "عدد الوحدات النصية تحت هذا الكتاب"
        ],
        [
          "كِتَابُ الطَّلَاقِ",
          152,
          3.06,
          "عدد الوحدات النصية تحت هذا الكتاب"
        ],
        [
          "كِتَابُ الزَّكَاةِ",
          135,
          2.71,
          "عدد الوحدات النصية تحت هذا الكتاب"
        ],
        [
          "كِتَابُ الْحُدُودِ",
          103,
          2.07,
          "عدد الوحدات النصية تحت هذا الكتاب"
        ],
        [
          "كِتَابُ الْأَشْرِبَةِ",
          99,
          1.99,
          "عدد الوحدات النصية تحت هذا الكتاب"
        ]
      ]
    },
    "executive_summary": {
      "_columns": [
        "البيان",
        "القيمة",
        "ملاحظة"
      ],
      "rows": [
        [
          "عنوان الكتاب",
          "شرح معاني الآثار",
          "من بطاقة EPUB"
        ],
        [
          "المؤلف",
          "أبو جعفر الطحاوي",
          "توصيف مرقوم"
        ],
        [
          "عدد الوحدات النصية المفهرسة",
          4975,
          "وحدات مستخرجة من كامل الملف"
        ],
        [
          "عدد عناوين الكتب والأبواب",
          362,
          "عناوين بنيوية غير مكررة قدر الإمكان"
        ],
        [
          "عدد الكتب بحسب الفهرس",
          27,
          "من جدول المحتويات"
        ],
        [
          "عدد الأبواب/العناوين الفرعية بحسب الفهرس",
          337,
          "من جدول المحتويات"
        ],
        [
          "أعلى رقم حديث ظاهر في الترقيم",
          7467,
          "وفق بيانات الملف"
        ],
        [
          "عدد الأجزاء",
          4,
          "وفق الترقيم الداخلي"
        ],
        [
          "آخر صفحة مطبوعة مرصودة",
          517,
          "وفق بيانات الملف"
        ],
        [
          "عدد الكلمات التقريبي",
          1850285,
          "حساب آلي تقريبي"
        ],
        [
          "المجال الموضوعي",
          "عدد الوحدات",
          "النسبة %"
        ],
        [
          "الصلاة",
          1198,
          24.08
        ],
        [
          "البيوع والمعاملات",
          1101,
          22.13
        ],
        [
          "الجنايات والحدود",
          1010,
          20.3
        ],
        [
          "الحج والمناسك",
          484,
          9.73
        ],
        [
          "الطهارة",
          387,
          7.78
        ],
        [
          "النكاح والطلاق",
          298,
          5.99
        ],
        [
          "الزكاة والصدقات",
          219,
          4.4
        ],
        [
          "الصوم",
          153,
          3.08
        ],
        [
          "المواريث والوصايا",
          65,
          1.31
        ],
        [
          "القضاء والشهادات",
          24,
          0.48
        ],
        [
          "السير والآداب",
          23,
          0.46
        ],
        [
          "الأيمان والنذور",
          13,
          0.26
        ],
        [
          "تنبيه منهجي",
          null,
          null
        ],
        [
          "النسب هنا نسب حضور آلية داخل النص المفهرس، وليست حكماً على مقدار اعتماد المؤلف بإطلاق.",
          null,
          null
        ],
        [
          "الكشاف التفصيلي مبني على كامل ملف EPUB المرفوع، وكل صف يمثل وحدة نصية أو عنواناً بنيوياً في ترتيب الكتاب.",
          null,
          null
        ],
        [
          "استخدمت مؤشرات لفظية لاستخراج الموارد والأعلام والمدارس، ولذلك تصلح النتائج للفهرسة والاستكشاف وتحتاج تدقيقاً علمياً عند النشر النهائي.",
          null,
          null
        ]
      ]
    }
  },
  "distributions": {},
  "limits": []
}